saturn_client/__init__.py
saturn_client/_version.py
saturn_client/core.py
saturn_client/file_syncs.py
saturn_client/logs.py
saturn_client/run.py
saturn_client/settings.py
saturn_client/tar_utils.py
saturn_client/cli/__init__.py
saturn_client/cli/commands.py
saturn_client/cli/utils.py
saturn_client-2025.10.5.dist-info/licenses/LICENSE
saturn_client-2025.10.5.dist-info/METADATA
saturn_client-2025.10.5.dist-info/WHEEL
saturn_client-2025.10.5.dist-info/entry_points.txt
saturn_client-2025.10.5.dist-info/top_level.txt
saturn_client-2025.10.5.dist-info/RECORD
