Metadata-Version: 2.4
Name: saturn-client
Version: 2025.10.5
Summary: Python library for interacting with Saturn Cloud API
Home-page: https://saturncloud.io/
Maintainer: Saturn Cloud Developers
Maintainer-email: dev@saturncloud.io
License: BSD-3-Clause
Project-URL: Documentation, http://docs.saturncloud.io
Project-URL: Source, https://github.com/saturncloud/saturn-client
Project-URL: Issue Tracker, https://github.com/saturncloud/saturn-client/issues
Keywords: saturn cloud client library
Classifier: Development Status :: 4 - Beta
Classifier: License :: OSI Approved :: BSD License
Classifier: Intended Audience :: Developers
Classifier: Intended Audience :: Science/Research
Classifier: Topic :: Scientific/Engineering
Classifier: Topic :: System :: Distributed Computing
Classifier: Programming Language :: Python :: 3
Classifier: Programming Language :: Python :: 3.7
Classifier: Programming Language :: Python :: 3.8
License-File: LICENSE
Requires-Dist: requests
Requires-Dist: fsspec>=2024.2
Requires-Dist: saturnfs
Requires-Dist: ruamel.yaml
Requires-Dist: cytoolz
Dynamic: classifier
Dynamic: description
Dynamic: description-content-type
Dynamic: home-page
Dynamic: keywords
Dynamic: license
Dynamic: license-file
Dynamic: maintainer
Dynamic: maintainer-email
Dynamic: project-url
Dynamic: requires-dist
Dynamic: summary
